README.md
setup.cfg
setup.py
lung/__init__.py
lung.egg-info/PKG-INFO
lung.egg-info/SOURCES.txt
lung.egg-info/dependency_links.txt
lung.egg-info/requires.txt
lung.egg-info/top_level.txt
lung/controllers/__init__.py
lung/controllers/_ada_pi.py
lung/controllers/_learned_bias.py
lung/controllers/_lookahead.py
lung/controllers/_original_pid.py
lung/controllers/_pid.py
lung/controllers/_predictive_bias_pi.py
lung/controllers/_predictive_pid.py
lung/controllers/core.py
lung/environments/__init__.py
lung/environments/_balloon.py
lung/environments/_delay_lung.py
lung/environments/_demo_lung.py
lung/environments/core.py
lung/utils/__init__.py
lung/utils/experiment.py