Metadata-Version: 2.1
Name: lung
Version: 0.1.4
Summary: Lung simulation
Home-page: https://github.com/MinRegret/Ventilator-Dev
Author: MinRegret
Author-email: minregret@minimizingregret.com
License: UNKNOWN
Platform: UNKNOWN
Provides-Extra: dev
